README.md
setup.py
pulumi_confluent/__init__.py
pulumi_confluent/_utilities.py
pulumi_confluent/api_key.py
pulumi_confluent/confluent_environment.py
pulumi_confluent/connector.py
pulumi_confluent/get_environment.py
pulumi_confluent/get_service_account.py
pulumi_confluent/kafka_cluster.py
pulumi_confluent/provider.py
pulumi_confluent/pulumi-plugin.json
pulumi_confluent/py.typed
pulumi_confluent/schema_registry.py
pulumi_confluent/service_account.py
pulumi_confluent.egg-info/PKG-INFO
pulumi_confluent.egg-info/SOURCES.txt
pulumi_confluent.egg-info/dependency_links.txt
pulumi_confluent.egg-info/not-zip-safe
pulumi_confluent.egg-info/requires.txt
pulumi_confluent.egg-info/top_level.txt
pulumi_confluent/config/__init__.py
pulumi_confluent/config/vars.py