Metadata-Version: 2.1
Name: pulumi-confluent
Version: 0.2.3a1645656874
Summary: A Pulumi package for creating and managing confluent cloud resources.
Home-page: https://pulumi.io
License: Apache-2.0
Project-URL: Repository, https://github.com/pulumi/pulumi-confluent
Keywords: pulumi confluent
Platform: UNKNOWN
